pyt2s/__init__.py
pyt2s/services/acapela.py
pyt2s/services/cepstral.py
pyt2s/services/hume.py
pyt2s/services/oddcast.py
pyt2s/services/speechify.py
pyt2s/services/streamlabs.py
pyt2s/services/voice_forge.py
pyt2s/voices/acapela.py
pyt2s/voices/cepstral.py
pyt2s/voices/hume.py
pyt2s/voices/oddcast.py
pyt2s/voices/speechify.py
pyt2s/voices/stream_labs.py
pyt2s/voices/voice_forge.py
pyt2s-0.0.6.dist-info/licenses/LICENSE
pyt2s-0.0.6.dist-info/METADATA
pyt2s-0.0.6.dist-info/WHEEL
pyt2s-0.0.6.dist-info/top_level.txt
pyt2s-0.0.6.dist-info/RECORD
