Metadata-Version: 2.4
Name: pyt2s
Version: 0.0.6
Summary: Python library you need for text to speech.
Author-email: Sumanth Perambuduri <sumanthpera444@gmail.com>
Project-URL: Homepage, https://github.com/supersu-man/pyt2s
Project-URL: Issues, https://github.com/supersu-man/pyt2s/issues
Classifier: Programming Language :: Python :: 3
Classifier: License :: OSI Approved :: MIT License
Classifier: Operating System :: OS Independent
License-File: LICENSE
Requires-Dist: requests
Dynamic: license-file
